PyBingRAG
