Metadata-Version: 2.1
Name: PyBingRAG
Version: 0.0.6
Summary: Python wrapper for Bing Search and RAG extraction
Home-page: https://github.com/Vishnunkumar/PyBingRAG/
Author: Vishnu Nandakumar
Author-email: nkumarvishnu25@gmail.com
License: MIT license
Keywords: bing search python
Classifier: Development Status :: 3 - Alpha
Classifier: Intended Audience :: Developers
Classifier: Topic :: Software Development :: Build Tools
Classifier: License :: OSI Approved :: MIT License
Classifier: Programming Language :: Python :: 3
Classifier: Programming Language :: Python :: 3.4
Classifier: Programming Language :: Python :: 3.5
Classifier: Programming Language :: Python :: 3.6
License-File: LICENSE
Requires-Dist: beautifulsoup4
Requires-Dist: langchain
Requires-Dist: numpy
Requires-Dist: sentence_transformers
Requires-Dist: scikit-learn
